{"cameraMode":{"drawMode":0,"name":"Shaded","section":"Shading Mode"},"sceneLighting":true,"audioPlay":false,"sceneViewState":{"m_AlwaysRefresh":false,"showFog":true,"showSkybox":true,"showFlares":true,"showImageEffects":false,"showParticleSystems":true,"showVisualEffectGraphs":true,"m_FxEnabled":true},"in2DMode":false,"pivot":{"x":58.39589309692383,"y":-62.739601135253909,"z":114.41259765625},"rotation":{"x":-0.3090909421443939,"y":-0.11885040998458862,"z":0.038966093212366107,"w":-0.9427759647369385},"size":50.1064453125,"orthographic":true}